diagonal/__init__.py
diagonal-0.0.2.dist-info/LICENSE.txt
diagonal-0.0.2.dist-info/METADATA
diagonal-0.0.2.dist-info/WHEEL
diagonal-0.0.2.dist-info/top_level.txt
diagonal-0.0.2.dist-info/RECORD
