Metadata-Version: 2.1
Name: diagonal
Version: 0.0.2
Summary: A small collection of functions to get various diagonals of a 2d matrix
Home-page: UNKNOWN
Author: opxyc
License: UNKNOWN
Platform: UNKNOWN
Classifier: Programming Language :: Python :: 3
Classifier: License :: OSI Approved :: MIT License
Classifier: Operating System :: OS Independent
